libnamegen/__init__.py
libnamegen/classic.py
libnamegen/random.py
libnamegen-3.1.1.post2.dist-info/LICENSE
libnamegen-3.1.1.post2.dist-info/METADATA
libnamegen-3.1.1.post2.dist-info/WHEEL
libnamegen-3.1.1.post2.dist-info/top_level.txt
libnamegen-3.1.1.post2.dist-info/RECORD
