Metadata-Version: 2.1
Name: libnamegen
Version: 3.1.1.post2
Summary: Library containing name generation methods
Home-page: https://git.bbaovanc.com/bbaovanc/libnamegen
Author: BBaoVanC
Author-email: pypi@bbaovanc.com
License: UNKNOWN
Platform: UNKNOWN
Classifier: Programming Language :: Python :: 3
Classifier: License :: OSI Approved :: GNU General Public License v3 (GPLv3)
Classifier: Operating System :: OS Independent
Requires-Python: >=3.7
License-File: LICENSE
Requires-Dist: libprogress (<4)
Requires-Dist: liblistloader (<2)
